agent_framework_neo4j/__init__.py
agent_framework_neo4j/_config.py
agent_framework_neo4j/_embedder.py
agent_framework_neo4j/_fulltext.py
agent_framework_neo4j/_memory.py
agent_framework_neo4j/_provider.py
agent_framework_neo4j/_settings.py
agent_framework_neo4j/_stop_words.py
agent_framework_neo4j-0.4.0.dist-info/WHEEL
agent_framework_neo4j-0.4.0.dist-info/METADATA
agent_framework_neo4j-0.4.0.dist-info/RECORD
