Metadata-Version: 2.4
Name: agent-framework-neo4j
Version: 0.4.0
Summary: Neo4j Context Provider for Microsoft Agent Framework - RAG with knowledge graphs
Keywords: neo4j,knowledge-graph,rag,context-provider,agent-framework,llm,vector-search,graph-database
Author-email: Microsoft <af-support@microsoft.com>
Requires-Python: >=3.10
Classifier: Development Status :: 4 - Beta
Classifier: Intended Audience :: Developers
Classifier: License :: OSI Approved :: MIT License
Classifier: Operating System :: OS Independent
Classifier: Programming Language :: Python :: 3
Classifier: Programming Language :: Python :: 3.10
Classifier: Programming Language :: Python :: 3.11
Classifier: Programming Language :: Python :: 3.12
Classifier: Topic :: Scientific/Engineering :: Artificial Intelligence
Classifier: Topic :: Database
Classifier: Typing :: Typed
Requires-Dist: agent-framework-core>=1.0.0b
Requires-Dist: neo4j>=5.0.0
Requires-Dist: neo4j-graphrag>=1.0.0
Requires-Dist: pydantic>=2.0.0
Requires-Dist: pydantic-settings>=2.0.0
Requires-Dist: azure-identity>=1.19.0 ; extra == "azure"
Requires-Dist: azure-ai-inference>=1.0.0b7 ; extra == "azure"
Project-URL: homepage, https://aka.ms/agent-framework
Project-URL: issues, https://github.com/microsoft/agent-framework/issues
Project-URL: source, https://github.com/microsoft/agent-framework/tree/main/python
Provides-Extra: azure
